stockcharts/__init__.py
stockcharts/cli.py
stockcharts/charts/__init__.py
stockcharts/charts/divergence.py
stockcharts/charts/heiken_ashi.py
stockcharts/data/__init__.py
stockcharts/data/fetch.py
stockcharts/indicators/__init__.py
stockcharts/indicators/divergence.py
stockcharts/indicators/pivots.py
stockcharts/indicators/rsi.py
stockcharts/screener/__init__.py
stockcharts/screener/nasdaq.py
stockcharts/screener/rsi_divergence.py
stockcharts/screener/screener.py
stockcharts-0.5.0.dist-info/licenses/LICENSE
stockcharts-0.5.0.dist-info/METADATA
stockcharts-0.5.0.dist-info/WHEEL
stockcharts-0.5.0.dist-info/entry_points.txt
stockcharts-0.5.0.dist-info/top_level.txt
stockcharts-0.5.0.dist-info/RECORD
