Metadata-Version: 2.4
Name: stockcharts
Version: 0.5.0
Summary: NASDAQ stock screener using Heiken Ashi candles and RSI divergence for trend reversal detection with volume and price filtering
Author-email: Paul Boys <paul.d.boys@gmail.com>
License-Expression: MIT
Project-URL: Homepage, https://github.com/paulboys/HeikinAshi
Project-URL: Repository, https://github.com/paulboys/HeikinAshi
Project-URL: Issues, https://github.com/paulboys/HeikinAshi/issues
Keywords: stocks,nasdaq,heiken ashi,rsi,divergence,screener,trading,finance,technical-analysis,swing-trading
Classifier: Development Status :: 4 - Beta
Classifier: Intended Audience :: Financial and Insurance Industry
Classifier: Topic :: Office/Business :: Financial :: Investment
Classifier: Programming Language :: Python :: 3
Classifier: Programming Language :: Python :: 3.9
Classifier: Programming Language :: Python :: 3.10
Classifier: Programming Language :: Python :: 3.11
Classifier: Programming Language :: Python :: 3.12
Classifier: Operating System :: OS Independent
Requires-Python: >=3.9
License-File: LICENSE
Requires-Dist: yfinance>=0.2.38
Requires-Dist: pandas>=2.0.0
Requires-Dist: matplotlib>=3.7.0
Requires-Dist: numpy>=1.24.0
Provides-Extra: dev
Requires-Dist: pytest>=7.0.0; extra == "dev"
Requires-Dist: ruff>=0.1.0; extra == "dev"
Dynamic: license-file
